pyfantasy/__init__.py
pyfantasy/fantasyapi.py
pyfantasy/utils.py
pyfantasy/yahoo_oauth.py
pyfantasy-0.1.dist-info/DESCRIPTION.rst
pyfantasy-0.1.dist-info/METADATA
pyfantasy-0.1.dist-info/RECORD
pyfantasy-0.1.dist-info/WHEEL
pyfantasy-0.1.dist-info/metadata.json
pyfantasy-0.1.dist-info/top_level.txt
