Metadata-Version: 2.0
Name: pyfantasy
Version: 0.1
Summary: An unofficial API to view and modify a Yahoo Fantasy team.
Home-page: http://github.com/ma-schmidt/pyfantasy
Author: Marc-Antoine Schmidt
Author-email: marc.a.schmidt@gmail.com
License: MIT
Platform: UNKNOWN
Requires-Dist: pyyaml
Requires-Dist: rauth
Requires-Dist: xmltodict
